telethon_client_wrapper/__init__.py
telethon_client_wrapper/client.py
telethon_client_wrapper/test_client.py
telethon_client_wrapper-0.9.9.dist-info/METADATA
telethon_client_wrapper-0.9.9.dist-info/WHEEL
telethon_client_wrapper-0.9.9.dist-info/entry_points.txt
telethon_client_wrapper-0.9.9.dist-info/top_level.txt
telethon_client_wrapper-0.9.9.dist-info/RECORD
