Metadata-Version: 2.1
Name: telethon_client_wrapper
Version: 0.9.9
Summary: A simple Telegram (telethon) client wrapper
Home-page: https://github.com/Rerowros/telethon_client_wrapper
Author: Ray
Classifier: Programming Language :: Python :: 3
Classifier: License :: OSI Approved :: MIT License
Classifier: Operating System :: OS Independent
Requires-Python: >=3.6
Requires-Dist: telethon
